{
  "regular_features": {
    "beer_garden": {
      "name": "Beer Garden",
      "description": "Enjoy our spacious beer garden with a great selection of craft beers",
      "availability": "Weather permitting",
      "seating": "First come, first served"
    },
    "sports": {
      "name": "Sports Viewing",
      "description": "Home of Berlin Irish Rugby Club - watch major rugby matches and other sports",
      "note": "Check our social media for match schedules"
    },
    "self_service": {
      "name": "Self-Service Bar",
      "description": "Order at the bar, find a cozy spot, and enjoy!",
      "note": "No table service or reservations"
    }
  },
  "special_features": {
    "craft_beer": {
      "name": "Craft Beer Selection",
      "description": "20 taps featuring local and international craft beers",
      "rotation": "Regular rotation of new beers",
      "info": "Check Untappd for current selection"
    },
    "pizza": {
      "name": "Neapolitan Pizza",
      "description": "Authentic Italian pizza made fresh to order",
      "style": "Traditional Neapolitan style"
    }
  },
  "venue_info": {
    "atmosphere": "Casual, friendly neighborhood pub",
    "location": "Heart of Berlin Mitte",
    "specialties": ["Craft Beer", "Neapolitan Pizza", "Sports Viewing", "Beer Garden"]
  }
} 